fm_index/__init__.py
fm_index/__init__.pyi
fm_index/fm_index.cpython-314t-arm-linux-musleabihf.so
fm_index/py.typed
fm_index-2.3.0.dist-info/METADATA
fm_index-2.3.0.dist-info/WHEEL
fm_index-2.3.0.dist-info/licenses/LICENSE
fm_index.libs/libgcc_s-262c4f60.so.1
fm_index-2.3.0.dist-info/RECORD
